enigma_ai/__init__.py
enigma_ai/__main__.py
enigma_ai/fetched_repos.csv
enigma_ai/fetched_repos_with_code.joblib
enigma_ai/helper.md
enigma_ai/test.ipynb
enigma_ai/utils.py
enigma_ai/cost/__init__.py
enigma_ai/cost/performance.py
enigma_ai/cost/resources.py
enigma_ai/data/__init__.py
enigma_ai/data/process.py
enigma_ai/data/scrape.py
enigma_ai/finetuning/__init__.py
enigma_ai/finetuning/finetuneLora.py
enigma_ai/finetuning/finetuning_datasets.py
enigma_ai/finetuning/finetuning_utils.py
enigma_ai/finetuning/train.py
llm_finetuning/__init__.py
llm_finetuning/cli.py
llm_finetuning/finetuneLoRa1B.py
llm_finetuning/finetuneLora.py
llm_finetuning/finetuning_datasets.py
llm_finetuning/finetuning_utils.py
llm_finetuning/setup.py
llm_finetuning/train.py
enigma_ai-0.2.2.dist-info/LICENSE
enigma_ai-0.2.2.dist-info/METADATA
enigma_ai-0.2.2.dist-info/WHEEL
enigma_ai-0.2.2.dist-info/entry_points.txt
enigma_ai-0.2.2.dist-info/top_level.txt
enigma_ai-0.2.2.dist-info/RECORD
