Metadata-Version: 2.1
Name: enigma_ai
Version: 0.2.2
Summary: Tools for simple and efficient training of LLMs for code generation
Home-page: https://www.enigma-ai.com/
Author: Enigma AI
License: MIT
Project-URL: Source, https://github.com/ammarnasr/Customizable-Code-Assistant
Project-URL: Documentation, https://enigma-ai.readthedocs.io/
Classifier: Development Status :: 3 - Alpha
Classifier: Intended Audience :: Developers
Classifier: License :: OSI Approved :: MIT License
Classifier: Programming Language :: Python :: 3
Requires-Python: >=3.7
License-File: LICENSE
